read_dataframe/__init__.py
read_dataframe/rdf.py
read_dataframe-0.1.0.dist-info/METADATA
read_dataframe-0.1.0.dist-info/WHEEL
read_dataframe-0.1.0.dist-info/entry_points.txt
read_dataframe-0.1.0.dist-info/top_level.txt
read_dataframe-0.1.0.dist-info/RECORD
